.pre-commit-config.yaml
LICENSE.txt
MANIFEST.in
README.md
pyproject.toml
requirements.txt
setup.cfg
setup.py
src/__init__.py
src/astronautcount.egg-info/PKG-INFO
src/astronautcount.egg-info/SOURCES.txt
src/astronautcount.egg-info/dependency_links.txt
src/astronautcount.egg-info/entry_points.txt
src/astronautcount.egg-info/requires.txt
src/astronautcount.egg-info/top_level.txt
src/bot/__init__.py
src/bot/bot.py
src/handler/__init__.py
src/handler/gunicorn.py
src/handler/handler.py