Metadata-Version: 2.1
Name: astronautcount
Version: 0.1.0
Summary: UNKNOWN
Home-page: https://github.com/bjd2385/astronautbot
Author: Brandon Doyle
Author-email: bjd2385.linux@gmail.com
License: UNKNOWN
Project-URL: Bug Reports, https://github.com/bjd2385/astronautbot/issues
Project-URL: Source, https://github.com/bjd2385/astronautbot
Keywords: Astronaut,NASA
Platform: UNKNOWN
Requires-Python: >=3.9, <4
License-File: LICENSE.txt
